uiaccessclient/__init__.py
uiaccessclient/openapi/__init__.py
uiaccessclient/openapi/api_client.py
uiaccessclient/openapi/api_response.py
uiaccessclient/openapi/configuration.py
uiaccessclient/openapi/exceptions.py
uiaccessclient/openapi/rest.py
uiaccessclient/openapi/api/__init__.py
uiaccessclient/openapi/api/access_policy_api.py
uiaccessclient/openapi/api/credential_api.py
uiaccessclient/openapi/api/device_api.py
uiaccessclient/openapi/api/space_api.py
uiaccessclient/openapi/api/system_log_api.py
uiaccessclient/openapi/api/uni_fi_identity_api.py
uiaccessclient/openapi/api/user_api.py
uiaccessclient/openapi/api/visitor_api.py
uiaccessclient/openapi/models/__init__.py
uiaccessclient/openapi/models/access_policies_response.py
uiaccessclient/openapi/models/access_policy.py
uiaccessclient/openapi/models/access_policy_day_schedule.py
uiaccessclient/openapi/models/access_policy_holiday.py
uiaccessclient/openapi/models/access_policy_holiday_group.py
uiaccessclient/openapi/models/access_policy_holiday_group_response.py
uiaccessclient/openapi/models/access_policy_holiday_group_summary.py
uiaccessclient/openapi/models/access_policy_holiday_group_summary_response.py
uiaccessclient/openapi/models/access_policy_holiday_schedule.py
uiaccessclient/openapi/models/access_policy_response.py
uiaccessclient/openapi/models/access_policy_schedule.py
uiaccessclient/openapi/models/access_policy_schedule_response.py
uiaccessclient/openapi/models/access_policy_schedules_response.py
uiaccessclient/openapi/models/access_policy_week_schedule.py
uiaccessclient/openapi/models/assign_uni_fi_identity_user_group_resources_request.py
uiaccessclient/openapi/models/assign_uni_fi_identity_user_resources_request.py
uiaccessclient/openapi/models/assign_user_access_policy_request.py
uiaccessclient/openapi/models/assign_user_group_access_policy_request.py
uiaccessclient/openapi/models/assign_user_nfc_card_request.py
uiaccessclient/openapi/models/assign_user_pin_code_request.py
uiaccessclient-0.9.3.dist-info/METADATA
uiaccessclient-0.9.3.dist-info/WHEEL
uiaccessclient-0.9.3.dist-info/top_level.txt
uiaccessclient-0.9.3.dist-info/RECORD
