Metadata-Version: 2.2
Name: uiaccessclient
Version: 0.9.3
Summary: UniFi Access API
Project-URL: Source, https://github.com/hagen93/uiaccessclient
Project-URL: Documentation, https://core-config-gfoz.uid.alpha.ui.com/configs/unifi-access/api_reference.pdf
Keywords: UniFi Access API
Requires-Dist: aiohttp<4.0.0,>=3.11.11
Requires-Dist: urllib3<3.0.0,>=1.25.3
Requires-Dist: python_dateutil>=2.8.2
Requires-Dist: pydantic>=2
Requires-Dist: typing-extensions>=4.7.1
Dynamic: keywords
Dynamic: project-url
Dynamic: requires-dist
Dynamic: summary
